<?xml version="1.0" encoding="ISO-8859-1"?>
<!--
    Relacion de consultas para la generacion de DBF's  
-->
<process>

  <model>    
  </model>

  <dml>
    <unit id="CapturaCuestionarios">      
			<select id="trJanalVisitas">
				select          
					tc_janal_muestras.id_familia,
					cast(tc_janal_muestras.consecutivo as char(6)) as consecutiv,					
          tc_janal_muestras.upm	as cve_upm,				
					tr_janal_visitas.visita,					
				  tr_janal_visitas.nom_ent,
					tr_janal_visitas.fecha,
					date_format(tr_janal_visitas.hr_ini, '%H:%i') as hr_ini,
					date_format(tr_janal_visitas.hr_ter, '%H:%i') as hr_ter,
					cast(tc_janal_resultados.clave as decimal) as res,
				  tc_janal_muestras.rectif as recertific
				from
				  tr_janal_visitas				
        inner join 
          tc_janal_muestras on tr_janal_visitas.id_muestra = tc_janal_muestras.id_muestra
				inner join 
          tc_janal_resultados on tr_janal_visitas.id_resultado=tc_janal_resultados.id_resultado
        where 
				  ((tr_janal_visitas.id_resultado= {idResultado}) or (-1= {idResultado})) and 
          ((tc_janal_muestras.id_entidad= {idEntidad}) or (-1= {idEntidad})) and
          tc_janal_muestras.upm like '%{upm}%'
				order by
           tc_janal_muestras.ent,tc_janal_muestras.id_familia,tr_janal_visitas.visita
			</select>
      <select id="trJanalCaratula">
        select   				    
          tc_janal_muestras.id_familia,					
          tr_janal_caratula.consecutiv	,
          tr_janal_caratula.cve_upm	,         
          tr_janal_caratula.folio_cuest	,
          tr_janal_caratula.t_cuest	,
          tr_janal_caratula.nom_tit	,
          tr_janal_caratula.pat_tit	,
          tr_janal_caratula.mat_tit	,
          tr_janal_caratula.calle	,
          tr_janal_caratula.num_ext	,
          tr_janal_caratula.num_int	,
          tr_janal_caratula.colonia	,
          tr_janal_caratula.cp	,
          tr_janal_caratula.telef	,
          tr_janal_caratula.referencia	,
          tr_janal_caratula.entre_ca1	,
          tr_janal_caratula.entre_ca2	,
          tr_janal_caratula.calle_atra,          
					tr_janal_caratula.ent,
					tr_janal_caratula.mun,
					tr_janal_caratula.loc,
					tc_janal_muestras.rectif as recertific
        from 
          tr_janal_caratula
        inner join 
          tc_janal_muestras on tr_janal_caratula.id_muestra = tc_janal_muestras.id_muestra
        left join 
          tr_janal_visitas on tc_janal_muestras.id_muestra=tr_janal_visitas.id_muestra and tr_janal_visitas.id_visita in (select id_visita from (select id_muestra,max(id_visita) as id_visita	from tr_janal_visitas group by id_muestra) as visitas)          
        where 
					((tr_janal_visitas.id_resultado= {idResultado}) or (-1= {idResultado})) and 
          ((tc_janal_muestras.id_entidad= {idEntidad}) or (-1= {idEntidad})) and
          tc_janal_muestras.upm like '%{upm}%'
				order by
           tc_janal_muestras.ent,tc_janal_muestras.id_familia
      </select>
      <select id="trJanalPersonas">
        select        				     
          tc_janal_muestras.id_familia,
					tr_janal_personas.consecutiv,
          tr_janal_personas.cve_upm	,
					tr_janal_personas.id_persona as id_per,
					tr_janal_personas.folio_cuest,          					
          tr_janal_personas.rg,
          tr_janal_personas.a_paterno,
          tr_janal_personas.a_materno,
          tr_janal_personas.nombre	,
          tr_janal_personas.c_resid	,
          tr_janal_personas.sexo	,
          cast(tr_janal_personas.edad as decimal)as edad,
          tr_janal_personas.esc	,
          tr_janal_personas.parent	,
          tr_janal_personas.v_resid	,
          tr_janal_personas.alim	,
          tr_janal_personas.salud	,
          tr_janal_personas.educ	,
          tr_janal_personas.otros	,
          tr_janal_personas.ninguno	,
          cast(tr_janal_personas.a_apoyo	as decimal) as a_apoyo,
          tr_janal_personas.activo,
          tr_janal_personas.filter_1 as informante,
					tc_janal_muestras.rectif as recertific
        from 
          tr_janal_personas
        inner join 
          tc_janal_muestras on tr_janal_personas.id_muestra = tc_janal_muestras.id_muestra
        left join 
          tr_janal_visitas on tc_janal_muestras.id_muestra=tr_janal_visitas.id_muestra and tr_janal_visitas.id_visita in (select id_visita from (select id_muestra,max(id_visita) as id_visita	from tr_janal_visitas group by id_muestra) as visitas)          
        where 					
          activo in ('1','3') and
					((tr_janal_visitas.id_resultado= {idResultado}) or (-1= {idResultado})) and 
          ((tc_janal_muestras.id_entidad= {idEntidad}) or (-1= {idEntidad})) and
          tc_janal_muestras.upm like '%{upm}%'
				order by
           tc_janal_muestras.ent,tc_janal_muestras.id_familia,rg
      </select>
      <select id="trJanalFamilias">
        select   				   
          tc_janal_muestras.id_familia,
					tr_janal_familias.consecutiv,
          tr_janal_familias.cve_upm,
					tr_janal_familias.folio_cuest,	
          cast(tr_janal_familias.mp_fr_re as char(1)) as mp_fr_re,
          cast(tr_janal_familias.mp_asist as char(1)) as mp_asist,
          cast(tr_janal_familias.mp_inf	as char(1)) as mp_inf,
				  cast(tr_janal_familias.t_salud as char(1)) as t_salud,
          cast(tr_janal_familias.t_alim as char(1)) as t_alim,
          cast(tr_janal_familias.t_adic as char(1)) as t_adic,
          cast(tr_janal_familias.t_planfa as char(1)) as t_planfa,
          cast(tr_janal_familias.t_edu as char(1)) as t_edu,
          cast(tr_janal_familias.t_progra as char(1)) as t_progra,
          cast(tr_janal_familias.t_otros as char(1)) as t_otros,
					tr_janal_familias.t_especi,
          cast(tr_janal_familias.mp_tmpo as char(1)) as mp_tmpo,
          cast(tr_janal_familias.mp_trto as char(1)) as mp_trto,
          cast(tr_janal_familias.a_mejora as char(1)) as a_mejora,
          cast(tr_janal_familias.a_sat as char(1)) as a_sat,
          cast(tr_janal_familias.a_oprt as char(1)) as a_oprt,
          cast(tr_janal_familias.a_sat_t as char(1)) as a_sat_t,
          cast(tr_janal_familias.a_otorga as char(1)) as a_otorga,
          cast(tr_janal_familias.a_esc_be as decimal) as a_esc_be,
          cast(tr_janal_familias.s_c_fv as char(1)) as s_c_fv,
          cast(tr_janal_familias.s_pl_fv_a as char(1)) as s_pl_fv_a,
          cast(tr_janal_familias.s_sat_c as char(1)) as s_sat_c,
          cast(tr_janal_familias.s_oprt_m as char(1)) as s_oprt_m,	
          cast(tr_janal_familias.s_s_t_c as char(1)) as s_s_t_c,
          cast(tr_janal_familias.s_s_pla as char(1)) as s_s_pla,
          cast(tr_janal_familias.s_s_t_pl as char(1)) as s_s_t_pl,
          cast(tr_janal_familias.s_otroga as char(1)) as s_otorga,
          cast(tr_janal_familias.s_p_fv_s as char(1)) as s_p_fv_s,
          cast(tr_janal_familias.s_p_emb as char(1)) as s_p_emb,
          cast(tr_janal_familias.s_p_adic as char(1)) as s_p_adic,
          cast(tr_janal_familias.s_esc_c as decimal) as s_esc_c,
          cast(tr_janal_familias.s_esc_m as decimal) as s_esc_m,
          cast(tr_janal_familias.s_esc_as as decimal) as s_esc_as,
          cast(tr_janal_familias.am_alim as char(1)) as am_alim,
          cast(tr_janal_familias.am_oport as char(1)) as am_oport,
          cast(tr_janal_familias.am_salud as char(1)) as am_salud,
          cast(tr_janal_familias.am_otorg as char(1)) as am_otorg,
          cast(tr_janal_familias.am_sat as char(1)) as am_sat,
          cast(tr_janal_familias.am_esc as decimal) as am_esc,
          cast(tr_janal_familias.e_nivel as char(1)) as e_nivel,
          cast(tr_janal_familias.e_cont as char(1)) as e_cont,
          cast(tr_janal_familias.e_conc as char(1)) as e_conc,
          cast(tr_janal_familias.e_trto_t as char(1)) as e_trto_t,
          cast(tr_janal_familias.e_oport as char(1)) as e_oport,
          cast(tr_janal_familias.e_otorga as char(1)) as e_otorga,
          cast(tr_janal_familias.e_sat as char(1)) as e_sat,
          cast(tr_janal_familias.e_empleo as char(1)) as e_empleo,	
          cast(tr_janal_familias.e_esc_e as decimal) as e_esc_e,
          cast(tr_janal_familias.at_pp as char(1)) as at_pp,
          cast(tr_janal_familias.at_pp_sat as char(1)) as at_pp_sat,	
          cast(tr_janal_familias.at_pp_cap as char(1)) as at_pp_cap,
          cast(tr_janal_familias.cap_t as char(1)) as cap_t,
          cast(tr_janal_familias.cap_t_sat as char(1)) as cap_t_sat,
          cast(tr_janal_familias.cap_t_cap as char(1)) as cap_t_cap,
          cast(tr_janal_familias.or_fi as char(1)) as or_fi,
          cast(tr_janal_familias.or_fi_sat as char(1)) as or_fi_sat,
          cast(tr_janal_familias.or_fi_pf as char(1)) as or_fi_pf,
          cast(tr_janal_familias.ap_soc as char(1)) as ap_soc,
          cast(tr_janal_familias.ap_soc_sat as char(1)) as ap_soc_sat,
          cast(tr_janal_familias.ap_soc_nv as char(1)) as ap_soc_nv,
					tc_janal_muestras.rectif as recertific
        from 
          tr_janal_familias        
        inner join 
          tc_janal_muestras on tr_janal_familias.id_muestra = tc_janal_muestras.id_muestra
        left join 
          tr_janal_visitas on tc_janal_muestras.id_muestra=tr_janal_visitas.id_muestra and tr_janal_visitas.id_visita in (select id_visita from (select id_muestra,max(id_visita) as id_visita	from tr_janal_visitas group by id_muestra) as visitas)          
        where 
					((tr_janal_visitas.id_resultado= {idResultado}) or (-1= {idResultado})) and 
          ((tc_janal_muestras.id_entidad= {idEntidad}) or (-1= {idEntidad})) and
          tc_janal_muestras.upm like '%{upm}%'
				order by
           tc_janal_muestras.ent,tc_janal_muestras.id_familia
      </select>
      <select id="trJanalModulo">
        select 				  
          tc_janal_muestras.id_familia,
					tr_janal_modulo.consecutiv,
          tr_janal_modulo.cve_upm, 
				  tr_janal_modulo.folio_cuest,             					
          cast(tr_janal_modulo.pro_des as char(1)) as pro_des,
          cast(tr_janal_modulo.gr_trab as char(1)) as gr_trab,
          cast(tr_janal_modulo.gr_apo as char(1)) as gr_apo,
          cast(tr_janal_modulo.gr_pro_opo as char(1)) as gr_pro_opo,
          cast(tr_janal_modulo.gr_apo_mej as char(1)) as gr_apo_mej,
					tc_janal_muestras.rectif as recertific
        from 
          tr_janal_modulo
        inner join 
          tc_janal_muestras on tr_janal_modulo.id_muestra = tc_janal_muestras.id_muestra
        left join 
          tr_janal_visitas on tc_janal_muestras.id_muestra=tr_janal_visitas.id_muestra and tr_janal_visitas.id_visita in (select id_visita from (select id_muestra,max(id_visita) as id_visita	from tr_janal_visitas group by id_muestra) as visitas)          
        where 
					((tr_janal_visitas.id_resultado= {idResultado}) or (-1= {idResultado})) and 
          ((tc_janal_muestras.id_entidad= {idEntidad}) or (-1= {idEntidad})) and
          tc_janal_muestras.upm like '%{upm}%'
				order by
           tc_janal_muestras.ent,tc_janal_muestras.id_familia
      </select>
			<select id="tcJanalEntidades">
				select 				  
					ent,
          upper(entidad) as descripcion
				from
					tc_janal_muestras 
        left join 
          tr_janal_visitas on tc_janal_muestras.id_muestra=tr_janal_visitas.id_muestra and tr_janal_visitas.id_visita in (select id_visita from (select id_muestra,max(id_visita) as id_visita	from tr_janal_visitas group by id_muestra) as visitas)          
        where 
					((tr_janal_visitas.id_resultado= {idResultado}) or (-1= {idResultado})) and 
          ((tc_janal_muestras.id_entidad= {idEntidad}) or (-1= {idEntidad})) and
          tc_janal_muestras.upm like '%{upm}%'
				group by
					ent,entidad
				order by
					ent
			</select>
			<select id="tcJanalMunicipios">
				select 				  
					ent,
          cve_mun as mun,
          upper(tc_janal_muestras.mun) as descripcion
				from
					tc_janal_muestras 
        left join 
          tr_janal_visitas on tc_janal_muestras.id_muestra=tr_janal_visitas.id_muestra and tr_janal_visitas.id_visita in (select id_visita from (select id_muestra,max(id_visita) as id_visita	from tr_janal_visitas group by id_muestra) as visitas)          
        where 
					((tr_janal_visitas.id_resultado= {idResultado}) or (-1= {idResultado})) and 
          ((tc_janal_muestras.id_entidad= {idEntidad}) or (-1= {idEntidad})) and
          tc_janal_muestras.upm like '%{upm}%'
				group by
				  ent,cve_mun,mun
				order by
				  ent,cve_mun
			</select>
			<select id="tcJanalLocalidades">
				select 				  
					ent,
          cve_mun as mun,
          loc,
          upper(localidad) as descripcion
				from
					tc_janal_muestras 
       left join 
          tr_janal_visitas on tc_janal_muestras.id_muestra=tr_janal_visitas.id_muestra and tr_janal_visitas.id_visita in (select id_visita from (select id_muestra,max(id_visita) as id_visita	from tr_janal_visitas group by id_muestra) as visitas)          
        where 
					((tr_janal_visitas.id_resultado= {idResultado}) or (-1= {idResultado})) and 
          ((tc_janal_muestras.id_entidad= {idEntidad}) or (-1= {idEntidad})) and
          tc_janal_muestras.upm like '%{upm}%'
				group by
				  ent,cve_mun,loc,localidad
				order by
					ent,cve_mun,loc
			</select>
    </unit>
  </dml>
</process>
